youqu_html_rpc/__init__.py
youqu_html_rpc/__version__.py
youqu_html_rpc/config.py
youqu_html_rpc/environment.py
youqu_html_rpc/server.py
youqu_html_rpc-2024.10.25.dist-info/METADATA
youqu_html_rpc-2024.10.25.dist-info/WHEEL
youqu_html_rpc-2024.10.25.dist-info/licenses/LICENSE
youqu_html_rpc-2024.10.25.dist-info/RECORD
