Metadata-Version: 2.1
Name: youqu-html-rpc
Version: 2024.10.25
Author-email: mikigo <huangmingqiang@uniontech.com>
License: GPL2.0
License-File: LICENSE
Requires-Python: >=3.7
Requires-Dist: funnylog2
Requires-Dist: pexpect
Provides-Extra: server
Requires-Dist: youqu-html; extra == 'server'
